aioclustermanager/__init__.py
aioclustermanager/deploy.py
aioclustermanager/deploy_list.py
aioclustermanager/exceptions.py
aioclustermanager/execution.py
aioclustermanager/executions_list.py
aioclustermanager/job.py
aioclustermanager/job_list.py
aioclustermanager/manager.py
aioclustermanager/node.py
aioclustermanager/node_list.py
aioclustermanager/service.py
aioclustermanager/statefulset.py
aioclustermanager/statefulset_list.py
aioclustermanager/utils.py
aioclustermanager/k8s/__init__.py
aioclustermanager/k8s/caller.py
aioclustermanager/k8s/const.py
aioclustermanager/k8s/delete.py
aioclustermanager/k8s/deploy.py
aioclustermanager/k8s/deploy_list.py
aioclustermanager/k8s/execution.py
aioclustermanager/k8s/executions_list.py
aioclustermanager/k8s/job.py
aioclustermanager/k8s/job_list.py
aioclustermanager/k8s/namespace.py
aioclustermanager/k8s/node.py
aioclustermanager/k8s/node_list.py
aioclustermanager/k8s/quota.py
aioclustermanager/k8s/scale.py
aioclustermanager/k8s/service.py
aioclustermanager/k8s/statefulset.py
aioclustermanager/k8s/statefulset_list.py
aioclustermanager/k8s/tf_job.py
aioclustermanager/k8s/tf_job_list.py
aioclustermanager/nomad/__init__.py
aioclustermanager/nomad/caller.py
aioclustermanager/nomad/const.py
aioclustermanager/nomad/execution.py
aioclustermanager/nomad/executions_list.py
aioclustermanager/nomad/job.py
aioclustermanager/nomad/job_list.py
aioclustermanager/nomad/namespace.py
aioclustermanager/nomad/node.py
aioclustermanager/nomad/node_list.py
aioclustermanager/tests/__init__.py
aioclustermanager/tests/conftest.py
aioclustermanager/tests/fixtures.py
aioclustermanager/tests/test_k8s.py
aioclustermanager/tests/test_nomad.py
aioclustermanager/tests/utils.py
aioclustermanager-0.3.44.dist-info/LICENSE
aioclustermanager-0.3.44.dist-info/METADATA
aioclustermanager-0.3.44.dist-info/WHEEL
aioclustermanager-0.3.44.dist-info/top_level.txt
aioclustermanager-0.3.44.dist-info/RECORD
