Metadata-Version: 2.2
Name: aioclustermanager
Version: 0.3.44
Summary: AsyncIO K8S and Nomad driver
Home-page: http://github.com/guillotinaweb/aioclustermanager
Author: Ramon Navarro
Author-email: ramon.nb@gmail.com
License: MIT
Classifier: Development Status :: 2 - Pre-Alpha
Classifier: Intended Audience :: Developers
Classifier: Programming Language :: Python :: 3.5
Classifier: Programming Language :: Python :: 3.6
License-File: LICENSE
Requires-Dist: aiohttp
Requires-Dist: python-dateutil
Dynamic: author
Dynamic: author-email
Dynamic: classifier
Dynamic: home-page
Dynamic: license
Dynamic: requires-dist
Dynamic: summary
